GTAlib_DataAdjust/__init__.py
GTAlib_DataAdjust/modulo.py
GTAlib_DataAdjust-0.1.4.dist-info/METADATA
GTAlib_DataAdjust-0.1.4.dist-info/WHEEL
GTAlib_DataAdjust-0.1.4.dist-info/top_level.txt
GTAlib_DataAdjust-0.1.4.dist-info/RECORD
