Metadata-Version: 2.1
Name: GTAlib-DataAdjust
Version: 0.1.4
Summary: Libreria para el ajuste de datos utilizando el método del kernel Gaussiano
Home-page: https://gitlab.com/gtorresa312/trabajos-en-clase.git
Author: German
Author-email: german.torres@udea.edu.co
License: MIT
Requires-Python: >=3.11.6
Requires-Dist: numpy ==1.26.1
Requires-Dist: pandas ==2.1.2
Requires-Dist: matplotlib ==3.8.1
